{
  "xml_id": "net.cakebuild.cakerider",
  "numeric_id": 15729,
  "versions": {
    "0.1.0": {
      "download_url": "https://downloads.marketplace.jetbrains.com/files/15729/107109/cake-rider-0.1.0.zip?updateId=107109&pluginId=15729&family=INTELLIJ",
      "sha256": "QZIZnnLBd+RyWORXP8knceevzaQSRNyPR41obJw3Co8=",
      "channel": "stable",
      "dependencies": [
        "com.intellij.modules.platform",
        "com.intellij.modules.rider"
      ],
      "optional_dependencies": [],
      "file_name": "cake-rider-0.1.0.zip"
    },
    "0.1.0-alpha.1": {
      "download_url": "https://downloads.marketplace.jetbrains.com/files/15729/106855/cake-rider-0.1.0-alpha.1.zip?updateId=106855&pluginId=15729&family=INTELLIJ",
      "sha256": "eOCjqoTOCgE6KDonR3xrx8bBPgwAZKQlnOq7X8oo5oQ=",
      "channel": "alpha",
      "dependencies": [
        "com.intellij.modules.platform",
        "com.intellij.modules.rider"
      ],
      "optional_dependencies": [],
      "file_name": "cake-rider-0.1.0-alpha.1.zip"
    },
    "0.2.0": {
      "download_url": "https://downloads.marketplace.jetbrains.com/files/15729/108104/cake-rider-0.2.0.zip?updateId=108104&pluginId=15729&family=INTELLIJ",
      "sha256": "lgRWRrZ28Ezx1FU0Gk1KDR28qcI2UBQA9xi+zdLoiZU=",
      "channel": "stable",
      "dependencies": [
        "com.intellij.modules.platform",
        "com.intellij.modules.rider"
      ],
      "optional_dependencies": [],
      "file_name": "cake-rider-0.2.0.zip"
    },
    "0.3.0": {
      "download_url": "https://downloads.marketplace.jetbrains.com/files/15729/115870/cake-rider-0.3.0.zip?updateId=115870&pluginId=15729&family=INTELLIJ",
      "sha256": "+Xs1yQeHBfSYxpUnafLaOSHt+NkP1lu+f8SPLPjo2s4=",
      "channel": "stable",
      "dependencies": [
        "com.intellij.modules.platform",
        "com.intellij.modules.rider"
      ],
      "optional_dependencies": [],
      "file_name": "cake-rider-0.3.0.zip"
    },
    "0.3.1": {
      "download_url": "https://downloads.marketplace.jetbrains.com/files/15729/116048/cake-rider-0.3.1.zip?updateId=116048&pluginId=15729&family=INTELLIJ",
      "sha256": "3x8cmr4b4P59SX9lPWw+FlGrpXLaktynNR2xuTPorYM=",
      "channel": "stable",
      "dependencies": [
        "com.intellij.modules.platform",
        "com.intellij.modules.rider"
      ],
      "optional_dependencies": [],
      "file_name": "cake-rider-0.3.1.zip"
    },
    "1.0.0": {
      "download_url": "https://downloads.marketplace.jetbrains.com/files/15729/121033/cake-rider-1.0.0.zip?updateId=121033&pluginId=15729&family=INTELLIJ",
      "sha256": "hP9xS0ouD6KQRIknX1CGPPHaSlG1yaNiXNIVSQ1jsjg=",
      "channel": "stable",
      "dependencies": [
        "com.intellij.modules.platform",
        "com.intellij.modules.rider"
      ],
      "optional_dependencies": [],
      "file_name": "cake-rider-1.0.0.zip"
    },
    "2.0.0": {
      "download_url": "https://downloads.marketplace.jetbrains.com/files/15729/130868/cake-rider-2.0.0.zip?updateId=130868&pluginId=15729&family=INTELLIJ",
      "sha256": "RtmFnMfCzOkA216FwbGjl71yu8YyFKSXL+5kLpLWDso=",
      "channel": "stable",
      "dependencies": [
        "com.intellij.modules.platform",
        "com.intellij.modules.rider"
      ],
      "optional_dependencies": [],
      "file_name": "cake-rider-2.0.0.zip"
    },
    "2.0.1": {
      "download_url": "https://downloads.marketplace.jetbrains.com/files/15729/133603/cake-rider-2.0.1.zip?updateId=133603&pluginId=15729&family=INTELLIJ",
      "sha256": "mRluBfqJUSUckvUrdtS39JVFLaGWLUfgzcXnL9OiAaI=",
      "channel": "stable",
      "dependencies": [
        "com.intellij.modules.platform",
        "com.intellij.modules.rider"
      ],
      "optional_dependencies": [],
      "file_name": "cake-rider-2.0.1.zip"
    },
    "2.0.2": {
      "download_url": "https://downloads.marketplace.jetbrains.com/files/15729/134019/cake-rider-2.0.2.zip?updateId=134019&pluginId=15729&family=INTELLIJ",
      "sha256": "fYoZVXHIq7Q1f1o8LNzGFePE9qRSklF2nQRU98pQ0lY=",
      "channel": "stable",
      "dependencies": [
        "com.intellij.modules.platform",
        "com.intellij.modules.rider"
      ],
      "optional_dependencies": [],
      "file_name": "cake-rider-2.0.2.zip"
    },
    "3.0.0": {
      "download_url": "https://downloads.marketplace.jetbrains.com/files/15729/148192/cake-rider-3.0.0.zip?updateId=148192&pluginId=15729&family=INTELLIJ",
      "sha256": "Bz0rvR4rd9VCAK1DAqdHMkllRtjGo0U0GZHVagNlVzc=",
      "channel": "stable",
      "dependencies": [
        "com.intellij.modules.platform",
        "com.intellij.modules.rider"
      ],
      "optional_dependencies": [],
      "file_name": "cake-rider-3.0.0.zip"
    },
    "3.1.0": {
      "download_url": "https://downloads.marketplace.jetbrains.com/files/15729/156317/cake-rider-3.1.0.zip?updateId=156317&pluginId=15729&family=INTELLIJ",
      "sha256": "NR3vfwrZtYoEi5VxRtkY1TcI59Zpx4FFoVZ1L5mGzpQ=",
      "channel": "stable",
      "dependencies": [
        "com.intellij.modules.platform",
        "com.intellij.modules.rider"
      ],
      "optional_dependencies": [],
      "file_name": "cake-rider-3.1.0.zip"
    },
    "3.2.0": {
      "download_url": "https://downloads.marketplace.jetbrains.com/files/15729/206020/cake-rider-3.2.0.zip?updateId=206020&pluginId=15729&family=INTELLIJ",
      "sha256": "W0hoYG5QIvQXVWeMm9jcUeldaQ0XmOmYs1xB5flTxYs=",
      "channel": "stable",
      "dependencies": [
        "com.intellij.modules.platform",
        "com.intellij.modules.rider"
      ],
      "optional_dependencies": [],
      "file_name": "cake-rider-3.2.0.zip"
    },
    "4.0.0": {
      "download_url": "https://downloads.marketplace.jetbrains.com/files/15729/231775/cake-rider-4.0.0.zip?updateId=231775&pluginId=15729&family=INTELLIJ",
      "sha256": "LxCOUVlsaxexaVUKLY0qciat/1GeZlLGJ9F4gFatmRI=",
      "channel": "stable",
      "dependencies": [
        "com.intellij.modules.platform",
        "com.intellij.modules.rider"
      ],
      "optional_dependencies": [],
      "file_name": "cake-rider-4.0.0.zip"
    },
    "4.1.0-bugfix-gh-301-0001": {
      "download_url": "https://downloads.marketplace.jetbrains.com/files/15729/265904/cake-rider-4.1.0-bugfix-gh-301-0001.zip?updateId=265904&pluginId=15729&family=INTELLIJ",
      "sha256": "ex59G7DNgvkSwDz0VwchdX3y+ECjRdCI6p6kLm2LTBY=",
      "channel": "beta",
      "dependencies": [
        "com.intellij.modules.platform",
        "com.intellij.modules.rider"
      ],
      "optional_dependencies": [],
      "file_name": "cake-rider-4.1.0-bugfix-gh-301-0001.zip"
    },
    "5.0.0": {
      "download_url": "https://downloads.marketplace.jetbrains.com/files/15729/266932/cake-rider-5.0.0.zip?updateId=266932&pluginId=15729&family=INTELLIJ",
      "sha256": "N0MpWyUFd/UPrAhW6emyoNOZp3Xe8GdFgETcy1E4Fec=",
      "channel": "stable",
      "dependencies": [
        "com.intellij.modules.platform",
        "com.intellij.modules.rider"
      ],
      "optional_dependencies": [],
      "file_name": "cake-rider-5.0.0.zip"
    },
    "6.0.0": {
      "download_url": "https://downloads.marketplace.jetbrains.com/files/15729/383057/cake-rider-6.0.0.zip?updateId=383057&pluginId=15729&family=INTELLIJ",
      "sha256": "/wxCN1oSqU+8S/A2Fc8ijrTiYOKcQESiixEaOltGQ9A=",
      "channel": "stable",
      "dependencies": [
        "com.intellij.modules.platform",
        "com.intellij.modules.rider"
      ],
      "optional_dependencies": [],
      "file_name": "cake-rider-6.0.0.zip"
    },
    "6.0.0-beta0001-0000": {
      "download_url": "https://downloads.marketplace.jetbrains.com/files/15729/383047/cake-rider-6.0.0-beta0001-0000.zip?updateId=383047&pluginId=15729&family=INTELLIJ",
      "sha256": "fBt+57kRs6OfP3OCr6dd9bd+zsOhi7AHLJ6bsz9goyg=",
      "channel": "beta",
      "dependencies": [
        "com.intellij.modules.platform",
        "com.intellij.modules.rider"
      ],
      "optional_dependencies": [],
      "file_name": "cake-rider-6.0.0-beta0001-0000.zip"
    },
    "7.0.0": {
      "download_url": "https://downloads.marketplace.jetbrains.com/files/15729/385585/cake-rider-7.0.0.zip?updateId=385585&pluginId=15729&family=INTELLIJ",
      "sha256": "kraC9RLi8yqe9gclq+CBvmcpEWZB72aWinBDU9Bm1Dw=",
      "channel": "stable",
      "dependencies": [
        "com.intellij.modules.platform",
        "com.intellij.modules.rider"
      ],
      "optional_dependencies": [],
      "file_name": "cake-rider-7.0.0.zip"
    },
    "7.1.0": {
      "download_url": "https://downloads.marketplace.jetbrains.com/files/15729/405264/cake-rider-7.1.0.zip?updateId=405264&pluginId=15729&family=INTELLIJ",
      "sha256": "B9KwXQwa0G96hC/huSKXVd5v4cjEIj/4j9xIZgLOO+c=",
      "channel": "stable",
      "dependencies": [
        "com.intellij.modules.platform",
        "com.intellij.modules.rider"
      ],
      "optional_dependencies": [],
      "file_name": "cake-rider-7.1.0.zip"
    },
    "8.0.1": {
      "download_url": "https://downloads.marketplace.jetbrains.com/files/15729/489368/cake-rider-8.0.1.zip?updateId=489368&pluginId=15729&family=INTELLIJ",
      "sha256": "5gpXm95+hQToYsewEE3Bz6LCpnBQmaxosT9ke5NaVQw=",
      "channel": "stable",
      "dependencies": [
        "com.intellij.modules.platform",
        "com.intellij.modules.rider"
      ],
      "optional_dependencies": [],
      "file_name": "cake-rider-8.0.1.zip"
    },
    "8.0.2": {
      "download_url": "https://downloads.marketplace.jetbrains.com/files/15729/534317/cake-rider-8.0.2.zip?updateId=534317&pluginId=15729&family=INTELLIJ",
      "sha256": "omqaIT2rUeZ41zi79Nd0Ceql1OYqHNi7zK5MkkGUpXc=",
      "channel": "stable",
      "dependencies": [
        "com.intellij.modules.platform",
        "com.intellij.modules.rider"
      ],
      "optional_dependencies": [],
      "file_name": "cake-rider-8.0.2.zip"
    },
    "8.0.2-pr426": {
      "download_url": "https://downloads.marketplace.jetbrains.com/files/15729/531923/cake-rider-8.0.2-pr426.zip?updateId=531923&pluginId=15729&family=INTELLIJ",
      "sha256": "Y+0rqqCLydQtxIrsiykE1qMaaHFx08EE1aLPSzWjVLs=",
      "channel": "beta",
      "dependencies": [
        "com.intellij.modules.platform",
        "com.intellij.modules.rider"
      ],
      "optional_dependencies": [],
      "file_name": "cake-rider-8.0.2-pr426.zip"
    }
  },
  "latest": {
    "alpha": "0.1.0-alpha.1",
    "beta": "8.0.2-pr426",
    "stable": "8.0.2"
  }
}