{
  "xml_id": "com.denghb.eorm.plugin",
  "numeric_id": 12618,
  "versions": {
    "1.0.1": {
      "download_url": "https://downloads.marketplace.jetbrains.com/files/12618/64536/eorm-idea-plugin.jar?updateId=64536&pluginId=12618&family=INTELLIJ",
      "sha256": "4PskwfdzkOrQ8jxcfwKUu5IaQSeNE4Q/QqL+2ea+oc4=",
      "channel": "stable",
      "dependencies": [
        "com.intellij.modules.lang"
      ],
      "optional_dependencies": [],
      "file_name": "eorm-idea-plugin.jar"
    },
    "1.0.2": {
      "download_url": "https://downloads.marketplace.jetbrains.com/files/12618/64862/eorm-idea-plugin.zip?updateId=64862&pluginId=12618&family=INTELLIJ",
      "sha256": "Hxm5GZqIvWEPS8poTimEDVBYjdUOemdni6guAAUJlms=",
      "channel": "stable",
      "dependencies": [
        "com.intellij.modules.lang"
      ],
      "optional_dependencies": [],
      "file_name": "eorm-idea-plugin.zip"
    },
    "1.0.3": {
      "download_url": "https://downloads.marketplace.jetbrains.com/files/12618/65814/eorm-idea-plugin.zip?updateId=65814&pluginId=12618&family=INTELLIJ",
      "sha256": "TUg/XeNs3XhQH8OxHvC9GLjEG+Um3EpUzHSKvbpt1Eg=",
      "channel": "stable",
      "dependencies": [
        "com.intellij.modules.lang"
      ],
      "optional_dependencies": [],
      "file_name": "eorm-idea-plugin.zip"
    },
    "1.0.4": {
      "download_url": "https://downloads.marketplace.jetbrains.com/files/12618/79632/eorm-idea-plugin.zip?updateId=79632&pluginId=12618&family=INTELLIJ",
      "sha256": "BdTBBMI98tBo8FAEmVbWpWDEhWS83C2TZbqAfaBUv38=",
      "channel": "stable",
      "dependencies": [
        "com.intellij.modules.lang"
      ],
      "optional_dependencies": [],
      "file_name": "eorm-idea-plugin.zip"
    },
    "1.0.5": {
      "download_url": "https://downloads.marketplace.jetbrains.com/files/12618/85517/eorm-idea-plugin.zip?updateId=85517&pluginId=12618&family=INTELLIJ",
      "sha256": "0vDUrxzaeDS0FrEyLdEOE9sLGzxpNfOcPv0rxOPjjNA=",
      "channel": "stable",
      "dependencies": [
        "com.intellij.modules.lang"
      ],
      "optional_dependencies": [],
      "file_name": "eorm-idea-plugin.zip"
    },
    "1.0.6": {
      "download_url": "https://downloads.marketplace.jetbrains.com/files/12618/107252/eorm-idea-plugin.zip?updateId=107252&pluginId=12618&family=INTELLIJ",
      "sha256": "ABhUD5uN8Tf45SSonnHcA6Y9m8cj90+rvbgj/jKFP20=",
      "channel": "stable",
      "dependencies": [
        "com.intellij.modules.lang"
      ],
      "optional_dependencies": [],
      "file_name": "eorm-idea-plugin.zip"
    }
  },
  "latest": {
    "stable": "1.0.6"
  }
}