{
  "xml_id": "com.baojieearth.javadoc",
  "numeric_id": 14619,
  "versions": {
    "1.0.0": {
      "download_url": "https://downloads.marketplace.jetbrains.com/files/14619/91437/javadoc-1.0.0.zip?updateId=91437&pluginId=14619&family=INTELLIJ",
      "sha256": "G1GtfMnXjdTW7IqasNnmMVL55O3qR+JEaoyqkuQQSZ0=",
      "channel": "stable",
      "dependencies": [
        "com.intellij.modules.platform"
      ],
      "optional_dependencies": [],
      "file_name": "javadoc-1.0.0.zip"
    }
  },
  "latest": {
    "stable": "1.0.0"
  }
}