{
  "xml_id": "ai.latta.tool",
  "numeric_id": 26032,
  "versions": {
    "1.0.1": {
      "download_url": "https://downloads.marketplace.jetbrains.com/files/26032/645667/intellij-1.0.1.zip?updateId=645667&pluginId=26032&family=INTELLIJ",
      "sha256": "dtvYeEX//3N+BKBoE2hrGX8CMSci8MdxntbUS/Th2eE=",
      "channel": "stable",
      "dependencies": [
        "com.intellij.modules.platform"
      ],
      "optional_dependencies": [],
      "file_name": "intellij-1.0.1.zip"
    },
    "1.0.2": {
      "download_url": "https://downloads.marketplace.jetbrains.com/files/26032/654682/tool-1.0.2.zip?updateId=654682&pluginId=26032&family=INTELLIJ",
      "sha256": "Qyzg2AeqHpIQxDAlkhW7U71KphdOKq9yOfiRD1EZe1g=",
      "channel": "stable",
      "dependencies": [
        "com.intellij.modules.platform"
      ],
      "optional_dependencies": [],
      "file_name": "tool-1.0.2.zip"
    }
  },
  "latest": {
    "stable": "1.0.2"
  }
}