{
  "xml_id": "io.github.xiaopihai7256",
  "numeric_id": 13022,
  "versions": {
    "0.1.0": {
      "download_url": "https://downloads.marketplace.jetbrains.com/files/13022/68966/MyGruvbox.jar?updateId=68966&pluginId=13022&family=INTELLIJ",
      "sha256": "M2E+r9pe5980KlklwcRev31Mug9D0upDxYDTXfzIGKA=",
      "channel": "stable",
      "dependencies": [],
      "optional_dependencies": [],
      "file_name": "MyGruvbox.jar"
    },
    "0.1.1": {
      "download_url": "https://downloads.marketplace.jetbrains.com/files/13022/68978/MyGruvbox.jar?updateId=68978&pluginId=13022&family=INTELLIJ",
      "sha256": "K6/KUcpomERQsfIGMOXnbeL5avG0g7j7Y6CGb4JP4rE=",
      "channel": "stable",
      "dependencies": [
        "com.intellij.modules.lang"
      ],
      "optional_dependencies": [],
      "file_name": "MyGruvbox.jar"
    },
    "0.2.0": {
      "download_url": "https://downloads.marketplace.jetbrains.com/files/13022/69151/MyGruvbox.jar?updateId=69151&pluginId=13022&family=INTELLIJ",
      "sha256": "zpbCmZ4SDzv9qT50voBYtvFLFIxLCAX3Zba21KBPhX4=",
      "channel": "stable",
      "dependencies": [
        "com.intellij.modules.lang"
      ],
      "optional_dependencies": [],
      "file_name": "MyGruvbox.jar"
    },
    "0.3.0": {
      "download_url": "https://downloads.marketplace.jetbrains.com/files/13022/72959/MyGruvbox.jar?updateId=72959&pluginId=13022&family=INTELLIJ",
      "sha256": "M3paXK/gtfei+5CWPLzevvgMGA0JhWADJQjVtKbIaUc=",
      "channel": "stable",
      "dependencies": [
        "com.intellij.modules.lang"
      ],
      "optional_dependencies": [],
      "file_name": "MyGruvbox.jar"
    },
    "0.3.1": {
      "download_url": "https://downloads.marketplace.jetbrains.com/files/13022/73886/MyGruvbox.jar?updateId=73886&pluginId=13022&family=INTELLIJ",
      "sha256": "CfGk12bcME8j7dRwcw/tS05aC7nsO/SNxU3YQCZD93A=",
      "channel": "stable",
      "dependencies": [
        "com.intellij.modules.lang"
      ],
      "optional_dependencies": [],
      "file_name": "MyGruvbox.jar"
    },
    "0.3.3": {
      "download_url": "https://downloads.marketplace.jetbrains.com/files/13022/94347/MyGruvbox.jar?updateId=94347&pluginId=13022&family=INTELLIJ",
      "sha256": "vekOAc7JgAZUHMxEeJKjsMZGbGxRmoRS0w+PLhEa7VQ=",
      "channel": "stable",
      "dependencies": [
        "com.intellij.modules.lang"
      ],
      "optional_dependencies": [],
      "file_name": "MyGruvbox.jar"
    },
    "0.4.0": {
      "download_url": "https://downloads.marketplace.jetbrains.com/files/13022/105253/MyGruvbox.jar?updateId=105253&pluginId=13022&family=INTELLIJ",
      "sha256": "CmldUrz0TsvP4RIsQ44x22nlTOrT4juQX1lc+xPxBT4=",
      "channel": "stable",
      "dependencies": [
        "com.intellij.modules.lang"
      ],
      "optional_dependencies": [],
      "file_name": "MyGruvbox.jar"
    },
    "0.5.0": {
      "download_url": "https://downloads.marketplace.jetbrains.com/files/13022/215494/MyGruvbox.jar?updateId=215494&pluginId=13022&family=INTELLIJ",
      "sha256": "awVgAY4Q8Yg+ZiVopbTs9PBvIRKI0eAvJzuEsKD08dA=",
      "channel": "stable",
      "dependencies": [
        "com.intellij.modules.lang"
      ],
      "optional_dependencies": [],
      "file_name": "MyGruvbox.jar"
    }
  },
  "latest": {
    "stable": "0.5.0"
  }
}