{
  "xml_id": "com.github.liff.dbexternalcommandauth",
  "numeric_id": 23933,
  "versions": {
    "0.0.1": {
      "download_url": "https://downloads.marketplace.jetbrains.com/files/23933/501706/db-external-command-auth-0.0.1-signed.zip?updateId=501706&pluginId=23933&family=INTELLIJ",
      "sha256": "DqWJ+reR2Be/q5EelI4tzrko6+dN3MuIDMG3927aQVg=",
      "channel": "stable",
      "dependencies": [
        "com.intellij.database",
        "com.intellij.modules.platform"
      ],
      "optional_dependencies": [],
      "file_name": "db-external-command-auth-0.0.1-signed.zip"
    },
    "0.0.2": {
      "download_url": "https://downloads.marketplace.jetbrains.com/files/23933/502625/db-external-command-auth-0.0.2.zip?updateId=502625&pluginId=23933&family=INTELLIJ",
      "sha256": "R1NJoCmlKWQrwOlGKPl2BP9r6ZwQ66yM9vxI52dzzpY=",
      "channel": "stable",
      "dependencies": [
        "com.intellij.database",
        "com.intellij.modules.platform"
      ],
      "optional_dependencies": [],
      "file_name": "db-external-command-auth-0.0.2.zip"
    },
    "0.1.0": {
      "download_url": "https://downloads.marketplace.jetbrains.com/files/23933/505892/db-external-command-auth-0.1.0.zip?updateId=505892&pluginId=23933&family=INTELLIJ",
      "sha256": "LI2ftGGPUITCAanbwvRRzxfUXtP8xpajqlfSSo0voeI=",
      "channel": "stable",
      "dependencies": [
        "com.intellij.database",
        "com.intellij.modules.platform"
      ],
      "optional_dependencies": [],
      "file_name": "db-external-command-auth-0.1.0.zip"
    },
    "0.2.0": {
      "download_url": "https://downloads.marketplace.jetbrains.com/files/23933/585091/db-external-command-auth-0.2.0.zip?updateId=585091&pluginId=23933&family=INTELLIJ",
      "sha256": "jDFzP+9YEdzpAqbjRqbJPvHFpBx2aZdWSCEjCEj5/cE=",
      "channel": "stable",
      "dependencies": [
        "com.intellij.database",
        "com.intellij.modules.platform"
      ],
      "optional_dependencies": [],
      "file_name": "db-external-command-auth-0.2.0.zip"
    },
    "1.0.0": {
      "download_url": "https://downloads.marketplace.jetbrains.com/files/23933/630572/db-external-command-auth-1.0.0.zip?updateId=630572&pluginId=23933&family=INTELLIJ",
      "sha256": "JATYDg2AHp38RLbN6S5V+32F/EQ71n46JQW0YH5Y0u8=",
      "channel": "stable",
      "dependencies": [
        "com.intellij.database",
        "com.intellij.modules.platform"
      ],
      "optional_dependencies": [],
      "file_name": "db-external-command-auth-1.0.0.zip"
    }
  },
  "latest": {
    "stable": "1.0.0"
  }
}