{
  "xml_id": "gruvbox-material-light",
  "numeric_id": 25592,
  "versions": {
    "1.0.1": {
      "download_url": "https://downloads.marketplace.jetbrains.com/files/25592/620938/gruvbox-material-light.jar?updateId=620938&pluginId=25592&family=INTELLIJ",
      "sha256": "fJFBJxng/6iPNoIMPZvgWAuxTc3LIXvudpJMCy7Da7g=",
      "channel": "stable",
      "dependencies": [
        "com.intellij.modules.platform"
      ],
      "optional_dependencies": [],
      "file_name": "gruvbox-material-light.jar"
    },
    "1.1.0": {
      "download_url": "https://downloads.marketplace.jetbrains.com/files/25592/622534/gruvbox-material-light.jar?updateId=622534&pluginId=25592&family=INTELLIJ",
      "sha256": "Vx4UpvzKrDHBMKjHU3iX+zNrtOBIeTK0xd5YVzmjZQE=",
      "channel": "stable",
      "dependencies": [
        "com.intellij.modules.platform"
      ],
      "optional_dependencies": [],
      "file_name": "gruvbox-material-light.jar"
    },
    "1.1.1": {
      "download_url": "https://downloads.marketplace.jetbrains.com/files/25592/625615/gruvbox-material-light.jar?updateId=625615&pluginId=25592&family=INTELLIJ",
      "sha256": "6ekJErIsExFV3vtfznmeZMxtfjuX4OuyCc58y43OM3I=",
      "channel": "stable",
      "dependencies": [
        "com.intellij.modules.platform"
      ],
      "optional_dependencies": [],
      "file_name": "gruvbox-material-light.jar"
    },
    "1.1.2": {
      "download_url": "https://downloads.marketplace.jetbrains.com/files/25592/634220/gruvbox-material-light.jar?updateId=634220&pluginId=25592&family=INTELLIJ",
      "sha256": "huE19y1PfTdwob5gQAcRXucLsuuxO/UsgXqO1LcfHIQ=",
      "channel": "stable",
      "dependencies": [
        "com.intellij.modules.platform"
      ],
      "optional_dependencies": [],
      "file_name": "gruvbox-material-light.jar"
    },
    "1.1.3": {
      "download_url": "https://downloads.marketplace.jetbrains.com/files/25592/640461/gruvbox-material-light.jar?updateId=640461&pluginId=25592&family=INTELLIJ",
      "sha256": "Tx0MxaAHktn4DSPRPj4etXMZsB72Cur8pGij8veQElY=",
      "channel": "stable",
      "dependencies": [
        "com.intellij.modules.platform"
      ],
      "optional_dependencies": [],
      "file_name": "gruvbox-material-light.jar"
    },
    "1.1.4": {
      "download_url": "https://downloads.marketplace.jetbrains.com/files/25592/650321/gruvbox-material-light.jar?updateId=650321&pluginId=25592&family=INTELLIJ",
      "sha256": "ixFrV0jfpBOa5f2dIIx6/jZaAQojZqPJEGrzEeOnTbw=",
      "channel": "stable",
      "dependencies": [
        "com.intellij.modules.platform"
      ],
      "optional_dependencies": [],
      "file_name": "gruvbox-material-light.jar"
    }
  },
  "latest": {
    "stable": "1.1.4"
  }
}