{
  "xml_id": "com.lightbc.templatej",
  "numeric_id": 21561,
  "versions": {
    "1.0.0-RELEASE": {
      "download_url": "https://downloads.marketplace.jetbrains.com/files/21561/327856/TemplateJ.zip?updateId=327856&pluginId=21561&family=INTELLIJ",
      "sha256": "L35/cqoVJJr1QGEmDyRswpAkunRj2y0Lcetjk56y4o4=",
      "channel": "stable",
      "dependencies": [
        "com.intellij.modules.database",
        "com.intellij.modules.java",
        "com.intellij.modules.lang",
        "com.intellij.modules.platform"
      ],
      "optional_dependencies": [],
      "file_name": "TemplateJ.zip"
    },
    "1.1.0-RELEASE": {
      "download_url": "https://downloads.marketplace.jetbrains.com/files/21561/328691/TemplateJ.zip?updateId=328691&pluginId=21561&family=INTELLIJ",
      "sha256": "vwrFgUXMNB+0woeAH1GZydJObtFGyXsTaqx7vQ15lEo=",
      "channel": "stable",
      "dependencies": [
        "com.intellij.modules.database",
        "com.intellij.modules.java",
        "com.intellij.modules.lang",
        "com.intellij.modules.platform"
      ],
      "optional_dependencies": [],
      "file_name": "TemplateJ.zip"
    },
    "1.1.1-RELEASE": {
      "download_url": "https://downloads.marketplace.jetbrains.com/files/21561/330524/TemplateJ.zip?updateId=330524&pluginId=21561&family=INTELLIJ",
      "sha256": "8tJWe+er/kXH5zEo1Y37nBbjsVcUIPu2LdWahIGz7ts=",
      "channel": "stable",
      "dependencies": [
        "com.intellij.modules.database",
        "com.intellij.modules.java",
        "com.intellij.modules.lang",
        "com.intellij.modules.platform"
      ],
      "optional_dependencies": [],
      "file_name": "TemplateJ.zip"
    },
    "1.1.2-RELEASE": {
      "download_url": "https://downloads.marketplace.jetbrains.com/files/21561/334169/TemplateJ.zip?updateId=334169&pluginId=21561&family=INTELLIJ",
      "sha256": "4j3ncY24969GG7sVXWKXbSMooG3oDHYR9ALhyFj5VRY=",
      "channel": "stable",
      "dependencies": [
        "com.intellij.modules.database",
        "com.intellij.modules.java",
        "com.intellij.modules.lang",
        "com.intellij.modules.platform"
      ],
      "optional_dependencies": [],
      "file_name": "TemplateJ.zip"
    },
    "1.1.3-RELEASE": {
      "download_url": "https://downloads.marketplace.jetbrains.com/files/21561/337593/TemplateJ.zip?updateId=337593&pluginId=21561&family=INTELLIJ",
      "sha256": "HRqyTE+5JGJw0uXeDYh+wlNOOU0SOuwbj2VTAMjtr50=",
      "channel": "stable",
      "dependencies": [
        "com.intellij.database",
        "com.intellij.modules.java",
        "com.intellij.modules.lang",
        "com.intellij.modules.platform"
      ],
      "optional_dependencies": [],
      "file_name": "TemplateJ.zip"
    },
    "1.1.4-RELEASE": {
      "download_url": "https://downloads.marketplace.jetbrains.com/files/21561/339577/TemplateJ.zip?updateId=339577&pluginId=21561&family=INTELLIJ",
      "sha256": "F47EKM7ppplLn5r3zJh0LS0jOwueTqrNTsUWqdO1CSw=",
      "channel": "stable",
      "dependencies": [
        "com.intellij.database",
        "com.intellij.modules.java",
        "com.intellij.modules.lang",
        "com.intellij.modules.platform"
      ],
      "optional_dependencies": [],
      "file_name": "TemplateJ.zip"
    },
    "1.2.0-RELEASE": {
      "download_url": "https://downloads.marketplace.jetbrains.com/files/21561/362106/TemplateJ.zip?updateId=362106&pluginId=21561&family=INTELLIJ",
      "sha256": "dnWOD3gNfOIL8R5fOplftb0iFfVfEjf805+vmZpV5E8=",
      "channel": "stable",
      "dependencies": [
        "com.intellij.database",
        "com.intellij.modules.java",
        "com.intellij.modules.lang",
        "com.intellij.modules.platform"
      ],
      "optional_dependencies": [],
      "file_name": "TemplateJ.zip"
    },
    "1.2.1-RELEASE": {
      "download_url": "https://downloads.marketplace.jetbrains.com/files/21561/365571/TemplateJ.zip?updateId=365571&pluginId=21561&family=INTELLIJ",
      "sha256": "2avwayfpx4wQplZGvjv2X3purMHuSSuO8JQXrKvKcbQ=",
      "channel": "stable",
      "dependencies": [
        "com.intellij.database",
        "com.intellij.modules.java",
        "com.intellij.modules.lang",
        "com.intellij.modules.platform"
      ],
      "optional_dependencies": [],
      "file_name": "TemplateJ.zip"
    },
    "1.2.2-RELEASE": {
      "download_url": "https://downloads.marketplace.jetbrains.com/files/21561/369591/TemplateJ.zip?updateId=369591&pluginId=21561&family=INTELLIJ",
      "sha256": "LY3S2lozcIL68L7kxsPYo6gYcZnXLZojb7Ujgrg3WuQ=",
      "channel": "stable",
      "dependencies": [
        "com.intellij.database",
        "com.intellij.modules.java",
        "com.intellij.modules.lang",
        "com.intellij.modules.platform"
      ],
      "optional_dependencies": [],
      "file_name": "TemplateJ.zip"
    },
    "1.2.3-RELEASE": {
      "download_url": "https://downloads.marketplace.jetbrains.com/files/21561/377523/TemplateJ.zip?updateId=377523&pluginId=21561&family=INTELLIJ",
      "sha256": "LMAgjA5heN86JbaLZ5Ss0oHj5YENrMfTfJNAew3lxjc=",
      "channel": "stable",
      "dependencies": [
        "com.intellij.database",
        "com.intellij.modules.java",
        "com.intellij.modules.lang",
        "com.intellij.modules.platform"
      ],
      "optional_dependencies": [],
      "file_name": "TemplateJ.zip"
    },
    "1.2.4-RELEASE": {
      "download_url": "https://downloads.marketplace.jetbrains.com/files/21561/445702/TemplateJ.zip?updateId=445702&pluginId=21561&family=INTELLIJ",
      "sha256": "NXeiiSZKAY9lAKCA7RsniEzFm6LxcAa+q19OY9RTvJI=",
      "channel": "stable",
      "dependencies": [
        "com.intellij.database",
        "com.intellij.modules.java",
        "com.intellij.modules.lang",
        "com.intellij.modules.platform"
      ],
      "optional_dependencies": [],
      "file_name": "TemplateJ.zip"
    },
    "1.3.0-RELEASE": {
      "download_url": "https://downloads.marketplace.jetbrains.com/files/21561/448140/TemplateJ.zip?updateId=448140&pluginId=21561&family=INTELLIJ",
      "sha256": "Xxo5iVlo+60EunOh3C+8yCmdEQQqo4hHwfcD4EA29bo=",
      "channel": "stable",
      "dependencies": [
        "com.intellij.database",
        "com.intellij.modules.java",
        "com.intellij.modules.lang",
        "com.intellij.modules.platform"
      ],
      "optional_dependencies": [],
      "file_name": "TemplateJ.zip"
    },
    "1.3.1-RELEASE": {
      "download_url": "https://downloads.marketplace.jetbrains.com/files/21561/451123/TemplateJ.zip?updateId=451123&pluginId=21561&family=INTELLIJ",
      "sha256": "Wc4fC6fC6wSPHmMXqopeqpjKLrWXvNOc6oMqO2vqIug=",
      "channel": "stable",
      "dependencies": [
        "com.intellij.database",
        "com.intellij.modules.java",
        "com.intellij.modules.lang",
        "com.intellij.modules.platform"
      ],
      "optional_dependencies": [],
      "file_name": "TemplateJ.zip"
    },
    "1.3.2-RELEASE": {
      "download_url": "https://downloads.marketplace.jetbrains.com/files/21561/452477/TemplateJ.zip?updateId=452477&pluginId=21561&family=INTELLIJ",
      "sha256": "dPP7+Tx1SSah2Vh0XZJM2dHFKZ9ZnEwY4lLvCDiFM8k=",
      "channel": "stable",
      "dependencies": [
        "com.intellij.database",
        "com.intellij.modules.java",
        "com.intellij.modules.lang",
        "com.intellij.modules.platform"
      ],
      "optional_dependencies": [],
      "file_name": "TemplateJ.zip"
    },
    "1.3.3-RELEASE": {
      "download_url": "https://downloads.marketplace.jetbrains.com/files/21561/453287/TemplateJ.zip?updateId=453287&pluginId=21561&family=INTELLIJ",
      "sha256": "66pWA2lZIJgsB5soG2KtB4BtJUg56m4/QSm4f1vSXu4=",
      "channel": "stable",
      "dependencies": [
        "com.intellij.database",
        "com.intellij.modules.java",
        "com.intellij.modules.lang",
        "com.intellij.modules.platform"
      ],
      "optional_dependencies": [],
      "file_name": "TemplateJ.zip"
    },
    "1.4.0-RELEASE": {
      "download_url": "https://downloads.marketplace.jetbrains.com/files/21561/457411/TemplateJ.zip?updateId=457411&pluginId=21561&family=INTELLIJ",
      "sha256": "wR0cXUIfFViw0F280bpzqjPQ56+Ss+7ZpDSLNG8ebLE=",
      "channel": "stable",
      "dependencies": [
        "com.intellij.database",
        "com.intellij.modules.java",
        "com.intellij.modules.lang",
        "com.intellij.modules.platform"
      ],
      "optional_dependencies": [],
      "file_name": "TemplateJ.zip"
    },
    "1.4.1-RELEASE": {
      "download_url": "https://downloads.marketplace.jetbrains.com/files/21561/458317/TemplateJ.zip?updateId=458317&pluginId=21561&family=INTELLIJ",
      "sha256": "vh9d7PRXdZRI2wfbTg0NmH5TG4SebK4bEAGwc5Y1r30=",
      "channel": "stable",
      "dependencies": [
        "com.intellij.database",
        "com.intellij.modules.java",
        "com.intellij.modules.lang",
        "com.intellij.modules.platform"
      ],
      "optional_dependencies": [],
      "file_name": "TemplateJ.zip"
    },
    "1.4.2-RELEASE": {
      "download_url": "https://downloads.marketplace.jetbrains.com/files/21561/460777/TemplateJ.zip?updateId=460777&pluginId=21561&family=INTELLIJ",
      "sha256": "dZYxyKe5r7LMol9c8kSkvTCO9ItGeRXEA9AvIeXIJh0=",
      "channel": "stable",
      "dependencies": [
        "com.intellij.database",
        "com.intellij.modules.java",
        "com.intellij.modules.lang",
        "com.intellij.modules.platform"
      ],
      "optional_dependencies": [],
      "file_name": "TemplateJ.zip"
    },
    "1.4.3-RELEASE": {
      "download_url": "https://downloads.marketplace.jetbrains.com/files/21561/467505/TemplateJ.zip?updateId=467505&pluginId=21561&family=INTELLIJ",
      "sha256": "14r3NGg5L9xjJjw4G3jQLhwaKVf8pESSUJYKuH2kNfk=",
      "channel": "stable",
      "dependencies": [
        "com.intellij.database",
        "com.intellij.modules.java",
        "com.intellij.modules.lang",
        "com.intellij.modules.platform"
      ],
      "optional_dependencies": [],
      "file_name": "TemplateJ.zip"
    }
  },
  "latest": {
    "stable": "1.4.3-RELEASE"
  }
}