{
  "xml_id": "co.anbora.labs.jmeter.plugins.manager",
  "numeric_id": 23812,
  "versions": {
    "1.0.1": {
      "download_url": "https://downloads.marketplace.jetbrains.com/files/23812/492356/JMeter_Plugins_Manager-1.0.1.zip?updateId=492356&pluginId=23812&family=INTELLIJ",
      "sha256": "BB8yNHnmem391Oaiv307szPv2aFox7x/54K7XP8RsPs=",
      "channel": "stable",
      "dependencies": [
        "co.anbora.labs.jmeter.jmeter-intellij",
        "com.intellij.modules.platform"
      ],
      "optional_dependencies": [],
      "file_name": "JMeter_Plugins_Manager-1.0.1.zip"
    },
    "1.0.2": {
      "download_url": "https://downloads.marketplace.jetbrains.com/files/23812/520007/JMeter_Plugins_Manager-1.0.2.zip?updateId=520007&pluginId=23812&family=INTELLIJ",
      "sha256": "M11jAZAckcDQc1IcKCvZT6Ei2DqLXVqSpi0KXyMVbcQ=",
      "channel": "stable",
      "dependencies": [
        "co.anbora.labs.jmeter.jmeter-intellij",
        "com.intellij.modules.platform"
      ],
      "optional_dependencies": [],
      "file_name": "JMeter_Plugins_Manager-1.0.2.zip"
    },
    "1.0.3": {
      "download_url": "https://downloads.marketplace.jetbrains.com/files/23812/520526/JMeter_Plugins_Manager-1.0.3.zip?updateId=520526&pluginId=23812&family=INTELLIJ",
      "sha256": "k2vEaHnrQ0kol+DSPZtWMOBVRg/FHIIfr2wkZzr/DRA=",
      "channel": "stable",
      "dependencies": [
        "co.anbora.labs.jmeter.jmeter-intellij",
        "com.intellij.modules.platform"
      ],
      "optional_dependencies": [],
      "file_name": "JMeter_Plugins_Manager-1.0.3.zip"
    },
    "1.1.0": {
      "download_url": "https://downloads.marketplace.jetbrains.com/files/23812/560626/jmeter-plugins-manager-intellij-1.1.0.zip?updateId=560626&pluginId=23812&family=INTELLIJ",
      "sha256": "y+hW2HFx4LQYKpzezsc22Z7mMBsmwM1pr9boeyuNgdM=",
      "channel": "stable",
      "dependencies": [
        "co.anbora.labs.jmeter.jmeter-intellij",
        "com.intellij.modules.platform"
      ],
      "optional_dependencies": [],
      "file_name": "jmeter-plugins-manager-intellij-1.1.0.zip"
    },
    "1.1.1": {
      "download_url": "https://downloads.marketplace.jetbrains.com/files/23812/604083/jmeter-plugins-manager-intellij-1.1.1.zip?updateId=604083&pluginId=23812&family=INTELLIJ",
      "sha256": "VvlemrWtyP7D/Lwmp25Vxwqvdm8CKlWAkGxc/qTNSMg=",
      "channel": "stable",
      "dependencies": [
        "co.anbora.labs.jmeter.jmeter-intellij",
        "com.intellij.modules.platform"
      ],
      "optional_dependencies": [],
      "file_name": "jmeter-plugins-manager-intellij-1.1.1.zip"
    },
    "1.1.2": {
      "download_url": "https://downloads.marketplace.jetbrains.com/files/23812/626932/jmeter-plugins-manager-intellij-1.1.2.zip?updateId=626932&pluginId=23812&family=INTELLIJ",
      "sha256": "UAFr0wH/CgCNYehWu+n7+b2/bYynLIdE/WMaqtIHol4=",
      "channel": "stable",
      "dependencies": [
        "co.anbora.labs.jmeter.jmeter-intellij",
        "com.intellij.modules.platform"
      ],
      "optional_dependencies": [],
      "file_name": "jmeter-plugins-manager-intellij-1.1.2.zip"
    },
    "1.2.0": {
      "download_url": "https://downloads.marketplace.jetbrains.com/files/23812/668418/jmeter-plugins-manager-intellij-1.2.0.zip?updateId=668418&pluginId=23812&family=INTELLIJ",
      "sha256": "Q7oFKsI8qRnT0+85d12TiwVZUf1EIZHDOR6O6P7f/Ik=",
      "channel": "stable",
      "dependencies": [
        "co.anbora.labs.jmeter.jmeter-intellij",
        "com.intellij.modules.platform"
      ],
      "optional_dependencies": [],
      "file_name": "jmeter-plugins-manager-intellij-1.2.0.zip"
    }
  },
  "latest": {
    "stable": "1.2.0"
  }
}