{
  "xml_id": "com.thtfpc.mybatis-log",
  "numeric_id": 14530,
  "versions": {
    "1.0.1": {
      "download_url": "https://downloads.marketplace.jetbrains.com/files/14530/89114/mybatis-log-1.0.1.zip?updateId=89114&pluginId=14530&family=INTELLIJ",
      "sha256": "s2clD+JmTXC0VOGEp8i1KJbqx5bilpLx0nDYWi6+gPo=",
      "channel": "stable",
      "dependencies": [
        "com.intellij.modules.platform"
      ],
      "optional_dependencies": [],
      "file_name": "mybatis-log-1.0.1.zip"
    },
    "1.0.2": {
      "download_url": "https://downloads.marketplace.jetbrains.com/files/14530/89304/mybatis-log-1.0.2.zip?updateId=89304&pluginId=14530&family=INTELLIJ",
      "sha256": "xtG+D6WP405WFtbUWxjKYtudPGm2kEk/A8jmVWC+S30=",
      "channel": "stable",
      "dependencies": [
        "com.intellij.modules.platform"
      ],
      "optional_dependencies": [],
      "file_name": "mybatis-log-1.0.2.zip"
    },
    "1.1.0": {
      "download_url": "https://downloads.marketplace.jetbrains.com/files/14530/106197/mybatis-log-1.1.0.zip?updateId=106197&pluginId=14530&family=INTELLIJ",
      "sha256": "Vve2iFNMoGNlqnh/PgmrHx1ZXxv87/iI7AduBQMrLKI=",
      "channel": "stable",
      "dependencies": [
        "com.intellij.modules.platform"
      ],
      "optional_dependencies": [],
      "file_name": "mybatis-log-1.1.0.zip"
    },
    "1.2.0": {
      "download_url": "https://downloads.marketplace.jetbrains.com/files/14530/107183/mybatis-log-1.2.0.zip?updateId=107183&pluginId=14530&family=INTELLIJ",
      "sha256": "oZELa00r+VKi1IxPxZc8yWyR0xaBYgCjYnwRtGtPnsQ=",
      "channel": "stable",
      "dependencies": [
        "com.intellij.modules.platform"
      ],
      "optional_dependencies": [],
      "file_name": "mybatis-log-1.2.0.zip"
    },
    "1.3.0": {
      "download_url": "https://downloads.marketplace.jetbrains.com/files/14530/107455/mybatis-log-1.3.0.zip?updateId=107455&pluginId=14530&family=INTELLIJ",
      "sha256": "bP2bQOS3HwuTenUSMXvc9KxRp0p9fvVdEtYaTwcxxFQ=",
      "channel": "stable",
      "dependencies": [
        "com.intellij.modules.platform"
      ],
      "optional_dependencies": [],
      "file_name": "mybatis-log-1.3.0.zip"
    },
    "1.3.1": {
      "download_url": "https://downloads.marketplace.jetbrains.com/files/14530/108164/mybatis-log-1.3.1.zip?updateId=108164&pluginId=14530&family=INTELLIJ",
      "sha256": "jjdjDFKs+dQf19nbzfH5477Hk3GNJc9pSBegKjn6voU=",
      "channel": "stable",
      "dependencies": [
        "com.intellij.modules.platform"
      ],
      "optional_dependencies": [],
      "file_name": "mybatis-log-1.3.1.zip"
    },
    "1.3.2": {
      "download_url": "https://downloads.marketplace.jetbrains.com/files/14530/108441/mybatis-log-1.3.2.zip?updateId=108441&pluginId=14530&family=INTELLIJ",
      "sha256": "cYpArlMAUqYQ7Jegr1ep0U4TfpGpQbMdNSbdx7Rd6Io=",
      "channel": "stable",
      "dependencies": [
        "com.intellij.modules.platform"
      ],
      "optional_dependencies": [],
      "file_name": "mybatis-log-1.3.2.zip"
    },
    "1.3.3": {
      "download_url": "https://downloads.marketplace.jetbrains.com/files/14530/108913/mybatis-log-1.3.3.zip?updateId=108913&pluginId=14530&family=INTELLIJ",
      "sha256": "MgADIPkQ2JBgBt3BXrw4bO4XcF9P1YGrYTEjXVPfFU4=",
      "channel": "stable",
      "dependencies": [
        "com.intellij.modules.platform"
      ],
      "optional_dependencies": [],
      "file_name": "mybatis-log-1.3.3.zip"
    },
    "1.3.4": {
      "download_url": "https://downloads.marketplace.jetbrains.com/files/14530/110262/mybatis-log-1.3.4.zip?updateId=110262&pluginId=14530&family=INTELLIJ",
      "sha256": "UFlkeNczw1PLtp9WW/Qm0y9mklwXHVG+lihml/OaxJM=",
      "channel": "stable",
      "dependencies": [
        "com.intellij.modules.platform"
      ],
      "optional_dependencies": [],
      "file_name": "mybatis-log-1.3.4.zip"
    },
    "1.4.0": {
      "download_url": "https://downloads.marketplace.jetbrains.com/files/14530/112783/mybatis-log-1.4.0.zip?updateId=112783&pluginId=14530&family=INTELLIJ",
      "sha256": "0ihddybIKnavgd8I7fmo4e6a+vw2i7uAn08j/uYjbxk=",
      "channel": "stable",
      "dependencies": [
        "com.intellij.modules.platform"
      ],
      "optional_dependencies": [],
      "file_name": "mybatis-log-1.4.0.zip"
    },
    "1.5.0": {
      "download_url": "https://downloads.marketplace.jetbrains.com/files/14530/116258/mybatis-log-1.5.0.zip?updateId=116258&pluginId=14530&family=INTELLIJ",
      "sha256": "/hKHIV0+k89FVcIqj37zTMAZbRDFebY8CDW+SWZ7+tc=",
      "channel": "stable",
      "dependencies": [
        "com.intellij.modules.platform"
      ],
      "optional_dependencies": [],
      "file_name": "mybatis-log-1.5.0.zip"
    },
    "1.5.1": {
      "download_url": "https://downloads.marketplace.jetbrains.com/files/14530/144452/mybatis-log-1.5.1.zip?updateId=144452&pluginId=14530&family=INTELLIJ",
      "sha256": "kdC88Empls4H264nIJagsqnZ0lSMALhYtiwmGTuSM1c=",
      "channel": "stable",
      "dependencies": [
        "com.intellij.modules.platform"
      ],
      "optional_dependencies": [],
      "file_name": "mybatis-log-1.5.1.zip"
    },
    "1.5.2": {
      "download_url": "https://downloads.marketplace.jetbrains.com/files/14530/144549/mybatis-log-1.5.2.zip?updateId=144549&pluginId=14530&family=INTELLIJ",
      "sha256": "nyCA06ara5JR4QDS8hRAH8kkooOB/edXm7raujsBDNk=",
      "channel": "stable",
      "dependencies": [
        "com.intellij.modules.platform"
      ],
      "optional_dependencies": [],
      "file_name": "mybatis-log-1.5.2.zip"
    },
    "2.0.0": {
      "download_url": "https://downloads.marketplace.jetbrains.com/files/14530/147017/mybatis-log-2.0.0.zip?updateId=147017&pluginId=14530&family=INTELLIJ",
      "sha256": "doBUlpKh/4BhV7LsROuAIT+YgdBPqKcOd3ss2zK7Ihk=",
      "channel": "stable",
      "dependencies": [
        "com.intellij.java",
        "com.intellij.modules.platform"
      ],
      "optional_dependencies": [],
      "file_name": "mybatis-log-2.0.0.zip"
    },
    "2.0.1": {
      "download_url": "https://downloads.marketplace.jetbrains.com/files/14530/147138/mybatis-log-2.0.1.zip?updateId=147138&pluginId=14530&family=INTELLIJ",
      "sha256": "OzlvuNfa9svXhXxeV0p7CxY1lOhCv3PG7ZDM859KMRI=",
      "channel": "stable",
      "dependencies": [
        "com.intellij.java",
        "com.intellij.modules.platform"
      ],
      "optional_dependencies": [],
      "file_name": "mybatis-log-2.0.1.zip"
    },
    "2.0.10": {
      "download_url": "https://downloads.marketplace.jetbrains.com/files/14530/166253/mybatis-log-2.0.10.zip?updateId=166253&pluginId=14530&family=INTELLIJ",
      "sha256": "K9zg/Y6fmQ+Pmb46KigWE6N9TxvzlhQlIL6yCyzGNbQ=",
      "channel": "stable",
      "dependencies": [
        "com.intellij.java",
        "com.intellij.modules.platform"
      ],
      "optional_dependencies": [],
      "file_name": "mybatis-log-2.0.10.zip"
    },
    "2.0.2": {
      "download_url": "https://downloads.marketplace.jetbrains.com/files/14530/148863/mybatis-log-2.0.2.zip?updateId=148863&pluginId=14530&family=INTELLIJ",
      "sha256": "djEpHyyvZtWO/FL+bGuYaaRCGJmNGxLNRjDb1fG97ns=",
      "channel": "stable",
      "dependencies": [
        "com.intellij.java",
        "com.intellij.modules.platform"
      ],
      "optional_dependencies": [],
      "file_name": "mybatis-log-2.0.2.zip"
    },
    "2.0.3": {
      "download_url": "https://downloads.marketplace.jetbrains.com/files/14530/149068/mybatis-log-2.0.3.zip?updateId=149068&pluginId=14530&family=INTELLIJ",
      "sha256": "vxbWsurVODNbY44HbSexJjUS/7mp/tikT7tFC5+pMOU=",
      "channel": "stable",
      "dependencies": [
        "com.intellij.java",
        "com.intellij.modules.platform"
      ],
      "optional_dependencies": [],
      "file_name": "mybatis-log-2.0.3.zip"
    },
    "2.0.4": {
      "download_url": "https://downloads.marketplace.jetbrains.com/files/14530/149502/mybatis-log-2.0.4.zip?updateId=149502&pluginId=14530&family=INTELLIJ",
      "sha256": "s32PeGjh+jj47P7pXnw0wVuYl91woyi/fBxqa+S+XgY=",
      "channel": "stable",
      "dependencies": [
        "com.intellij.java",
        "com.intellij.modules.platform"
      ],
      "optional_dependencies": [],
      "file_name": "mybatis-log-2.0.4.zip"
    },
    "2.0.5": {
      "download_url": "https://downloads.marketplace.jetbrains.com/files/14530/150039/mybatis-log-2.0.5.zip?updateId=150039&pluginId=14530&family=INTELLIJ",
      "sha256": "BmXyf1vbm51aG2CEyvJHoASPs0Vcx3UXXNieLTbMKM0=",
      "channel": "stable",
      "dependencies": [
        "com.intellij.java",
        "com.intellij.modules.platform"
      ],
      "optional_dependencies": [],
      "file_name": "mybatis-log-2.0.5.zip"
    },
    "2.0.6": {
      "download_url": "https://downloads.marketplace.jetbrains.com/files/14530/152397/mybatis-log-2.0.6.zip?updateId=152397&pluginId=14530&family=INTELLIJ",
      "sha256": "SD+X+i+tZfYOTFVujOrrbtmOyi5XUeWY7Kn+Jf62zu8=",
      "channel": "stable",
      "dependencies": [
        "com.intellij.java",
        "com.intellij.modules.platform"
      ],
      "optional_dependencies": [],
      "file_name": "mybatis-log-2.0.6.zip"
    },
    "2.0.7": {
      "download_url": "https://downloads.marketplace.jetbrains.com/files/14530/154175/mybatis-log-2.0.7.zip?updateId=154175&pluginId=14530&family=INTELLIJ",
      "sha256": "kmSzm0TUXP1l7OE8xwo/OEXTihRB8sK81PJTRakjmzY=",
      "channel": "stable",
      "dependencies": [
        "com.intellij.java",
        "com.intellij.modules.platform"
      ],
      "optional_dependencies": [],
      "file_name": "mybatis-log-2.0.7.zip"
    },
    "2.0.8": {
      "download_url": "https://downloads.marketplace.jetbrains.com/files/14530/154837/mybatis-log-2.0.8.zip?updateId=154837&pluginId=14530&family=INTELLIJ",
      "sha256": "DlxO/dIOqjLkLVN5+R8GEUedmjIUTENQ8Yg8mAQiTho=",
      "channel": "stable",
      "dependencies": [
        "com.intellij.java",
        "com.intellij.modules.platform"
      ],
      "optional_dependencies": [],
      "file_name": "mybatis-log-2.0.8.zip"
    },
    "2.0.9": {
      "download_url": "https://downloads.marketplace.jetbrains.com/files/14530/158919/mybatis-log-2.0.9.zip?updateId=158919&pluginId=14530&family=INTELLIJ",
      "sha256": "ba/tFBaISprJlQy4Noa4oLdbF60EZoCOFV1LWcaWw4o=",
      "channel": "stable",
      "dependencies": [
        "com.intellij.java",
        "com.intellij.modules.platform"
      ],
      "optional_dependencies": [],
      "file_name": "mybatis-log-2.0.9.zip"
    },
    "3.0.0": {
      "download_url": "https://downloads.marketplace.jetbrains.com/files/14530/203943/mybatis-log-3.0.0.zip?updateId=203943&pluginId=14530&family=INTELLIJ",
      "sha256": "zMd7zFlENmbNylkPGFMYWBTN74NpFBUCtyO1wUxM0Eg=",
      "channel": "stable",
      "dependencies": [
        "com.intellij.java",
        "com.intellij.modules.platform"
      ],
      "optional_dependencies": [],
      "file_name": "mybatis-log-3.0.0.zip"
    },
    "3.0.1": {
      "download_url": "https://downloads.marketplace.jetbrains.com/files/14530/204455/mybatis-log-3.0.1.zip?updateId=204455&pluginId=14530&family=INTELLIJ",
      "sha256": "r4iZCrbHss1PqjTbk5QjjjikCuwzKL+tb541lwmLCEU=",
      "channel": "stable",
      "dependencies": [
        "com.intellij.java",
        "com.intellij.modules.platform"
      ],
      "optional_dependencies": [],
      "file_name": "mybatis-log-3.0.1.zip"
    },
    "3.0.2": {
      "download_url": "https://downloads.marketplace.jetbrains.com/files/14530/206491/mybatis-log-3.0.2.zip?updateId=206491&pluginId=14530&family=INTELLIJ",
      "sha256": "kH6finGdVAQc1fN2kzIQLaTj+Ws4bRvmZdsdKWWpnP4=",
      "channel": "stable",
      "dependencies": [
        "com.intellij.java",
        "com.intellij.modules.platform"
      ],
      "optional_dependencies": [],
      "file_name": "mybatis-log-3.0.2.zip"
    },
    "3.0.3": {
      "download_url": "https://downloads.marketplace.jetbrains.com/files/14530/207020/mybatis-log-3.0.3.zip?updateId=207020&pluginId=14530&family=INTELLIJ",
      "sha256": "IxT9+6JlRmcHrRP1TaVAuITjwEkIr3c2+gzz18f8egg=",
      "channel": "stable",
      "dependencies": [
        "com.intellij.java",
        "com.intellij.modules.platform"
      ],
      "optional_dependencies": [],
      "file_name": "mybatis-log-3.0.3.zip"
    },
    "3.0.4": {
      "download_url": "https://downloads.marketplace.jetbrains.com/files/14530/228133/mybatis-log-3.0.4.zip?updateId=228133&pluginId=14530&family=INTELLIJ",
      "sha256": "VrDS2DkVMcgro9rJIYA5B5L6czF9uKgfT51z/wbyiuM=",
      "channel": "stable",
      "dependencies": [
        "com.intellij.java",
        "com.intellij.modules.platform"
      ],
      "optional_dependencies": [],
      "file_name": "mybatis-log-3.0.4.zip"
    }
  },
  "latest": {
    "stable": "3.0.4"
  }
}