{
  "xml_id": "com.dmitryzhelnin.intellij.plugin.gitextensions",
  "numeric_id": 11511,
  "versions": {
    "0.2.2": {
      "download_url": "https://downloads.marketplace.jetbrains.com/files/11511/53854/git-extensions-plugin-0.2.2.zip?updateId=53854&pluginId=11511&family=INTELLIJ",
      "sha256": "VS6MymFAnuNDkwJNvaGMAg+MZQIYVqB6op2ujNTeCNA=",
      "channel": "stable",
      "dependencies": [
        "com.intellij.modules.lang"
      ],
      "optional_dependencies": [],
      "file_name": "git-extensions-plugin-0.2.2.zip"
    },
    "0.3.1": {
      "download_url": "https://downloads.marketplace.jetbrains.com/files/11511/53965/git-extensions-plugin-0.3.1.zip?updateId=53965&pluginId=11511&family=INTELLIJ",
      "sha256": "evclf1MCwdLI/zxhXyyQtzzJ20ie5YnETOYYyQs8KeI=",
      "channel": "stable",
      "dependencies": [
        "com.intellij.modules.lang"
      ],
      "optional_dependencies": [],
      "file_name": "git-extensions-plugin-0.3.1.zip"
    },
    "0.4.0": {
      "download_url": "https://downloads.marketplace.jetbrains.com/files/11511/54138/git-extensions-plugin-0.4.0.zip?updateId=54138&pluginId=11511&family=INTELLIJ",
      "sha256": "5eqW0fnYjLC+vFN2LzNotIYbmS1GPHltk0n1ITlc/lI=",
      "channel": "stable",
      "dependencies": [
        "com.intellij.modules.lang"
      ],
      "optional_dependencies": [],
      "file_name": "git-extensions-plugin-0.4.0.zip"
    },
    "0.4.0-183": {
      "download_url": "https://downloads.marketplace.jetbrains.com/files/11511/54110/git-extensions-plugin-0.4.0-183.zip?updateId=54110&pluginId=11511&family=INTELLIJ",
      "sha256": "4TqQ93ltzXzaq4KaxxurieWzR/eppT0xaujcUzFZNuU=",
      "channel": "stable",
      "dependencies": [
        "com.intellij.modules.lang"
      ],
      "optional_dependencies": [],
      "file_name": "git-extensions-plugin-0.4.0-183.zip"
    },
    "0.4.1": {
      "download_url": "https://downloads.marketplace.jetbrains.com/files/11511/57719/git-extensions-plugin-0.4.1.zip?updateId=57719&pluginId=11511&family=INTELLIJ",
      "sha256": "W8212A1gJQE8NwKu+PZax2+Os0LFK7/U2XjbRTcuGq8=",
      "channel": "stable",
      "dependencies": [
        "com.intellij.modules.lang"
      ],
      "optional_dependencies": [],
      "file_name": "git-extensions-plugin-0.4.1.zip"
    },
    "0.4.2": {
      "download_url": "https://downloads.marketplace.jetbrains.com/files/11511/77922/git-extensions-plugin-0.4.2.zip?updateId=77922&pluginId=11511&family=INTELLIJ",
      "sha256": "Xm4EuJ2wfqk5ib6FU/CBAknt8LR9/43K7vG+DWZT+f0=",
      "channel": "stable",
      "dependencies": [
        "com.intellij.modules.lang"
      ],
      "optional_dependencies": [],
      "file_name": "git-extensions-plugin-0.4.2.zip"
    },
    "0.4.3": {
      "download_url": "https://downloads.marketplace.jetbrains.com/files/11511/99702/git-extensions-plugin-0.4.3.zip?updateId=99702&pluginId=11511&family=INTELLIJ",
      "sha256": "73f15LBxyusj45N8TdWimJFSzd2eD0a+3TIptPMYR1E=",
      "channel": "stable",
      "dependencies": [
        "com.intellij.modules.lang"
      ],
      "optional_dependencies": [],
      "file_name": "git-extensions-plugin-0.4.3.zip"
    },
    "0.4.4": {
      "download_url": "https://downloads.marketplace.jetbrains.com/files/11511/137262/git-extensions-plugin-0.4.4.zip?updateId=137262&pluginId=11511&family=INTELLIJ",
      "sha256": "buCRIf83FbaurXFTUrRCuJ9JQw0eRWhUncYQk/BbsqE=",
      "channel": "stable",
      "dependencies": [
        "com.intellij.modules.lang"
      ],
      "optional_dependencies": [],
      "file_name": "git-extensions-plugin-0.4.4.zip"
    }
  },
  "latest": {
    "stable": "0.4.4"
  }
}