{
  "xml_id": "co.com.devlinx9.k8s-cxts-selector-stbar",
  "numeric_id": 20612,
  "versions": {
    "1.0.1": {
      "download_url": "https://downloads.marketplace.jetbrains.com/files/20612/264095/kubernetes-context-selector-1.0.1.zip?updateId=264095&pluginId=20612&family=INTELLIJ",
      "sha256": "O/Mwcw2r7lKcY2CytIsPpvODBwuVlFfVv09ivKURrYA=",
      "channel": "stable",
      "dependencies": [
        "com.intellij.modules.platform"
      ],
      "optional_dependencies": [],
      "file_name": "kubernetes-context-selector-1.0.1.zip"
    },
    "2.0.0": {
      "download_url": "https://downloads.marketplace.jetbrains.com/files/20612/379421/kubernetes-context-selector-2.0.0.zip?updateId=379421&pluginId=20612&family=INTELLIJ",
      "sha256": "2fJsnNvnq7msMyWRoiZ4cnuxL6977gXvnnHTGKUYj1w=",
      "channel": "stable",
      "dependencies": [
        "com.intellij.modules.platform"
      ],
      "optional_dependencies": [],
      "file_name": "kubernetes-context-selector-2.0.0.zip"
    },
    "2.0.1": {
      "download_url": "https://downloads.marketplace.jetbrains.com/files/20612/385593/kubernetes-context-selector-2.0.1.zip?updateId=385593&pluginId=20612&family=INTELLIJ",
      "sha256": "5TZa68XL5jOG/4h23WmYSTuoFuPaS6Wvc6d+Q+mXeV0=",
      "channel": "stable",
      "dependencies": [
        "com.intellij.modules.platform"
      ],
      "optional_dependencies": [],
      "file_name": "kubernetes-context-selector-2.0.1.zip"
    },
    "2.0.2": {
      "download_url": "https://downloads.marketplace.jetbrains.com/files/20612/456879/kubernetes-context-selector-2.0.2.zip?updateId=456879&pluginId=20612&family=INTELLIJ",
      "sha256": "Cj/+fbiz6VCwwFnUpj9oh4c9/MKmhQIom2+CW1h+qto=",
      "channel": "stable",
      "dependencies": [
        "com.intellij.modules.platform"
      ],
      "optional_dependencies": [],
      "file_name": "kubernetes-context-selector-2.0.2.zip"
    },
    "2.0.3": {
      "download_url": "https://downloads.marketplace.jetbrains.com/files/20612/526130/kubernetes-context-selector-2.0.3.zip?updateId=526130&pluginId=20612&family=INTELLIJ",
      "sha256": "JSpWZFbtRBwLcR8/Xm2YPSebEz0J0tcNOErUBFrQfus=",
      "channel": "stable",
      "dependencies": [
        "com.intellij.modules.platform"
      ],
      "optional_dependencies": [],
      "file_name": "kubernetes-context-selector-2.0.3.zip"
    },
    "2.0.4": {
      "download_url": "https://downloads.marketplace.jetbrains.com/files/20612/619951/kubernetes-context-selector-2.0.4.zip?updateId=619951&pluginId=20612&family=INTELLIJ",
      "sha256": "TR9IrwVT4238M6jfEQeoAWhXSUyv2D/5YGD9zw+NVZ0=",
      "channel": "stable",
      "dependencies": [
        "com.intellij.modules.platform"
      ],
      "optional_dependencies": [],
      "file_name": "kubernetes-context-selector-2.0.4.zip"
    },
    "2.0.5": {
      "download_url": "https://downloads.marketplace.jetbrains.com/files/20612/643820/kubernetes-context-selector-2.0.5.zip?updateId=643820&pluginId=20612&family=INTELLIJ",
      "sha256": "EtxcA3RbcKSHcopp3EvAfJPa5wWqy5dVIyI1KDtRI0Y=",
      "channel": "stable",
      "dependencies": [
        "com.intellij.modules.platform"
      ],
      "optional_dependencies": [],
      "file_name": "kubernetes-context-selector-2.0.5.zip"
    },
    "2.0.6": {
      "download_url": "https://downloads.marketplace.jetbrains.com/files/20612/643935/kubernetes-context-selector-2.0.6.zip?updateId=643935&pluginId=20612&family=INTELLIJ",
      "sha256": "88JDOEFHdIwXquEpM5ZPQ9P/nQkHU822ZbaVTptNxgo=",
      "channel": "stable",
      "dependencies": [
        "com.intellij.modules.platform"
      ],
      "optional_dependencies": [],
      "file_name": "kubernetes-context-selector-2.0.6.zip"
    },
    "2.1.0": {
      "download_url": "https://downloads.marketplace.jetbrains.com/files/20612/682858/kubernetes-context-selector-2.1.0.zip?updateId=682858&pluginId=20612&family=INTELLIJ",
      "sha256": "d+EXLP3H/z3ieSNxrQU+PqQUtEOIYuh0ayo2r9EBq5Y=",
      "channel": "stable",
      "dependencies": [
        "com.intellij.modules.platform"
      ],
      "optional_dependencies": [],
      "file_name": "kubernetes-context-selector-2.1.0.zip"
    }
  },
  "latest": {
    "stable": "2.1.0"
  }
}