{
  "xml_id": "IdeaTwitter",
  "numeric_id": 1827,
  "versions": {
    "1.0": {
      "download_url": "https://downloads.marketplace.jetbrains.com/files/1827/4879/IdeaTwitter_4879.zip?updateId=4879&pluginId=1827&family=INTELLIJ",
      "sha256": "BLTTqt0s5odoolO79HXG00rs2eQe2Lv6b7lrDxtGisY=",
      "channel": "stable",
      "dependencies": [],
      "optional_dependencies": [],
      "file_name": "IdeaTwitter_4879.zip"
    },
    "1.0.1": {
      "download_url": "https://downloads.marketplace.jetbrains.com/files/1827/4880/IdeaTwitter_4880.zip?updateId=4880&pluginId=1827&family=INTELLIJ",
      "sha256": "nfVNgEvPaw+oE6NWl2BZdCwfQB2L0rigdGl60nZ69NE=",
      "channel": "stable",
      "dependencies": [],
      "optional_dependencies": [],
      "file_name": "IdeaTwitter_4880.zip"
    },
    "1.0.2": {
      "download_url": "https://downloads.marketplace.jetbrains.com/files/1827/5262/IdeaTwitter_5262.zip?updateId=5262&pluginId=1827&family=INTELLIJ",
      "sha256": "Lxh9hi6ORcZhnBKM1rCK4iKssjTcG1jJREuNQxZPaqw=",
      "channel": "stable",
      "dependencies": [],
      "optional_dependencies": [],
      "file_name": "IdeaTwitter_5262.zip"
    }
  },
  "latest": {
    "stable": "1.0.2"
  }
}