{
  "xml_id": "com.timindustries.regexpluginv2",
  "numeric_id": 21533,
  "versions": {
    "0.0.3": {
      "download_url": "https://downloads.marketplace.jetbrains.com/files/21533/323970/Regex_Helper-0.0.3-signed.zip?updateId=323970&pluginId=21533&family=INTELLIJ",
      "sha256": "2yQogNa2Jkl5X6DSHrCPGV4Bd4k7Q8XB+juC2jkA42Q=",
      "channel": "stable",
      "dependencies": [
        "com.intellij.modules.platform"
      ],
      "optional_dependencies": [],
      "file_name": "Regex_Helper-0.0.3-signed.zip"
    },
    "0.0.4": {
      "download_url": "https://downloads.marketplace.jetbrains.com/files/21533/324465/Regex_Helper-0.0.4-signed.zip?updateId=324465&pluginId=21533&family=INTELLIJ",
      "sha256": "69HgrLkKw3s/2TwCI6FbeovtU3MMyi2VxA5CQHmj9J4=",
      "channel": "stable",
      "dependencies": [
        "com.intellij.modules.platform"
      ],
      "optional_dependencies": [],
      "file_name": "Regex_Helper-0.0.4-signed.zip"
    },
    "0.0.5": {
      "download_url": "https://downloads.marketplace.jetbrains.com/files/21533/324468/Regex_Helper-0.0.5-signed.zip?updateId=324468&pluginId=21533&family=INTELLIJ",
      "sha256": "UTkImTPAlN3HUDfKAUmvvwW57ahb5UANHUANdHV8ZlY=",
      "channel": "stable",
      "dependencies": [
        "com.intellij.modules.platform"
      ],
      "optional_dependencies": [],
      "file_name": "Regex_Helper-0.0.5-signed.zip"
    },
    "0.0.6": {
      "download_url": "https://downloads.marketplace.jetbrains.com/files/21533/324485/Regex_Helper-0.0.6-signed.zip?updateId=324485&pluginId=21533&family=INTELLIJ",
      "sha256": "WXve5bkpVKlDyr7E2GzazZo6B2s1XxsJ/tI1Sw4x1FQ=",
      "channel": "stable",
      "dependencies": [
        "com.intellij.modules.platform"
      ],
      "optional_dependencies": [],
      "file_name": "Regex_Helper-0.0.6-signed.zip"
    },
    "0.0.7": {
      "download_url": "https://downloads.marketplace.jetbrains.com/files/21533/401342/Regex_Helper-0.0.7-signed.zip?updateId=401342&pluginId=21533&family=INTELLIJ",
      "sha256": "gk2ET8RJnSRH7rti/go4th/P1Phtzve24TI4MAmJZ7A=",
      "channel": "stable",
      "dependencies": [
        "com.intellij.modules.platform"
      ],
      "optional_dependencies": [],
      "file_name": "Regex_Helper-0.0.7-signed.zip"
    }
  },
  "latest": {
    "stable": "0.0.7"
  }
}