{
  "xml_id": "ru.sadv1r.afc.ideaPlugin",
  "numeric_id": 8096,
  "versions": {
    "0.1": {
      "download_url": "https://downloads.marketplace.jetbrains.com/files/8096/22831/AfcForCoders.jar?updateId=22831&pluginId=8096&family=INTELLIJ",
      "sha256": "8QRaixoAlYgWGe93qxUyK3KqpZWiPBCqhJveymm6dsc=",
      "channel": "stable",
      "dependencies": [],
      "optional_dependencies": [],
      "file_name": "AfcForCoders.jar"
    },
    "0.1.1": {
      "download_url": "https://downloads.marketplace.jetbrains.com/files/8096/22935/AfcForCoders.jar?updateId=22935&pluginId=8096&family=INTELLIJ",
      "sha256": "yqRMCxTOmK8yDcBAlfp0dY2eP4xhDqIf9GGNbFN5nnQ=",
      "channel": "stable",
      "dependencies": [],
      "optional_dependencies": [],
      "file_name": "AfcForCoders.jar"
    },
    "0.1.2": {
      "download_url": "https://downloads.marketplace.jetbrains.com/files/8096/22946/AfcForCoders.jar?updateId=22946&pluginId=8096&family=INTELLIJ",
      "sha256": "UPgDFCehWIwsF7ETLIgghVaM+Pg1rwN5gpNrkvwoVNc=",
      "channel": "stable",
      "dependencies": [],
      "optional_dependencies": [],
      "file_name": "AfcForCoders.jar"
    }
  },
  "latest": {
    "stable": "0.1.2"
  }
}