{
  "xml_id": "com.huawei.ide.oversea",
  "numeric_id": 11297,
  "versions": {
    "1.2.3": {
      "download_url": "https://downloads.marketplace.jetbrains.com/files/11297/51840/Huawei_IDE.zip?updateId=51840&pluginId=11297&family=INTELLIJ",
      "sha256": "TLRcXLBziD2uu5Du3aQ3JFwYb3WIRv4ZkFj7ehmnEJI=",
      "channel": "stable",
      "dependencies": [
        "Git4Idea",
        "org.jetbrains.android"
      ],
      "optional_dependencies": [],
      "file_name": "Huawei_IDE.zip"
    },
    "1.2.4": {
      "download_url": "https://downloads.marketplace.jetbrains.com/files/11297/53193/Huawei_IDE.zip?updateId=53193&pluginId=11297&family=INTELLIJ",
      "sha256": "dvD60vF9Ppid3lAqf5k5DOyH0bZQ7zpNkVhhisH1zJo=",
      "channel": "stable",
      "dependencies": [
        "Git4Idea",
        "org.jetbrains.android"
      ],
      "optional_dependencies": [],
      "file_name": "Huawei_IDE.zip"
    },
    "2.0.2019040": {
      "download_url": "https://downloads.marketplace.jetbrains.com/files/11297/63336/Huawei_IDE.zip?updateId=63336&pluginId=11297&family=INTELLIJ",
      "sha256": "92EfXQpL1GKI9iucajKHDvafL17z99xbhwmJRWSb9lg=",
      "channel": "stable",
      "dependencies": [
        "Git4Idea",
        "org.jetbrains.android"
      ],
      "optional_dependencies": [],
      "file_name": "Huawei_IDE.zip"
    }
  },
  "latest": {
    "stable": "2.0.2019040"
  }
}