{
  "xml_id": "com.machak.hippo.plugin.id",
  "numeric_id": 7226,
  "versions": {
    "1.0": {
      "download_url": "https://downloads.marketplace.jetbrains.com/files/7226/13212/hippo-shared-libs.jar?updateId=13212&pluginId=7226&family=INTELLIJ",
      "sha256": "EXNlY+zqhFYWEoOQ71Tv54Eq1ghDIIFV5+Kml78FA1c=",
      "channel": "stable",
      "dependencies": [],
      "optional_dependencies": [],
      "file_name": "hippo-shared-libs.jar"
    },
    "1.0.1": {
      "download_url": "https://downloads.marketplace.jetbrains.com/files/7226/13223/hippo-shared-libs.jar?updateId=13223&pluginId=7226&family=INTELLIJ",
      "sha256": "R3qifQ2O2DTNa5hT6E5gOeXmq1iI/BWPHEsK7izr6+4=",
      "channel": "stable",
      "dependencies": [],
      "optional_dependencies": [],
      "file_name": "hippo-shared-libs.jar"
    },
    "1.0.2": {
      "download_url": "https://downloads.marketplace.jetbrains.com/files/7226/13224/hippo-shared-libs.jar?updateId=13224&pluginId=7226&family=INTELLIJ",
      "sha256": "Irkjne2XBp0zrI34lFGrg+Zl8k+cDDngJ/UtEUA3sHM=",
      "channel": "stable",
      "dependencies": [],
      "optional_dependencies": [],
      "file_name": "hippo-shared-libs.jar"
    },
    "1.0.3": {
      "download_url": "https://downloads.marketplace.jetbrains.com/files/7226/14169/hippo-shared-libs.jar?updateId=14169&pluginId=7226&family=INTELLIJ",
      "sha256": "WrC9Lejxeg0vyHWSUp0T4+5zHoZ4PExwzPqIfCNnaSk=",
      "channel": "stable",
      "dependencies": [],
      "optional_dependencies": [],
      "file_name": "hippo-shared-libs.jar"
    },
    "1.0.4": {
      "download_url": "https://downloads.marketplace.jetbrains.com/files/7226/15157/hippo-shared-libs.jar?updateId=15157&pluginId=7226&family=INTELLIJ",
      "sha256": "7fAsFR/JaQjLxVw8835pNZUCOSxlJ83sYF7C3AtS5CE=",
      "channel": "stable",
      "dependencies": [],
      "optional_dependencies": [],
      "file_name": "hippo-shared-libs.jar"
    },
    "1.0.5": {
      "download_url": "https://downloads.marketplace.jetbrains.com/files/7226/15791/hippo-shared-libs.jar?updateId=15791&pluginId=7226&family=INTELLIJ",
      "sha256": "rThH+b90sHCN524NsGhDPJuwD9Ae711QbWLd8J4grFg=",
      "channel": "stable",
      "dependencies": [],
      "optional_dependencies": [],
      "file_name": "hippo-shared-libs.jar"
    },
    "1.0.6": {
      "download_url": "https://downloads.marketplace.jetbrains.com/files/7226/29525/hippo-shared-libs.zip?updateId=29525&pluginId=7226&family=INTELLIJ",
      "sha256": "KIpfEmePJo4JfArmW9wtO8FCjcu+laI3y39tY6nMduM=",
      "channel": "stable",
      "dependencies": [],
      "optional_dependencies": [],
      "file_name": "hippo-shared-libs.zip"
    },
    "1.0.7": {
      "download_url": "https://downloads.marketplace.jetbrains.com/files/7226/29652/hippo-shared-libs.zip?updateId=29652&pluginId=7226&family=INTELLIJ",
      "sha256": "YTZhtt3TUNgn8SYL+tRvbnsxW5mVnYXLo/qiXNG7A7k=",
      "channel": "stable",
      "dependencies": [],
      "optional_dependencies": [],
      "file_name": "hippo-shared-libs.zip"
    },
    "1.0.8": {
      "download_url": "https://downloads.marketplace.jetbrains.com/files/7226/29788/hippo-shared-libs.zip?updateId=29788&pluginId=7226&family=INTELLIJ",
      "sha256": "wOPBUl1/bL2oTNt4LyfArYeTjY4B9HTEKK97VXY9O0M=",
      "channel": "stable",
      "dependencies": [],
      "optional_dependencies": [],
      "file_name": "hippo-shared-libs.zip"
    },
    "1.0.9": {
      "download_url": "https://downloads.marketplace.jetbrains.com/files/7226/34403/hippo-shared-libs.zip?updateId=34403&pluginId=7226&family=INTELLIJ",
      "sha256": "Q6VumgDAIoMNoVk5Al3zciiwQu3AwdlgwPVlUkK8lcU=",
      "channel": "stable",
      "dependencies": [
        "Tomcat",
        "com.intellij.javaee"
      ],
      "optional_dependencies": [],
      "file_name": "hippo-shared-libs.zip"
    },
    "1.1.0": {
      "download_url": "https://downloads.marketplace.jetbrains.com/files/7226/39076/hippo-shared-libs.zip?updateId=39076&pluginId=7226&family=INTELLIJ",
      "sha256": "fG183L33OdRQeqzKY/yW41gWJEGzy7xneuGzcDCxtGk=",
      "channel": "stable",
      "dependencies": [
        "Tomcat",
        "com.intellij.javaee"
      ],
      "optional_dependencies": [],
      "file_name": "hippo-shared-libs.zip"
    },
    "1.2": {
      "download_url": "https://downloads.marketplace.jetbrains.com/files/7226/43081/hippo-shared-libs.zip?updateId=43081&pluginId=7226&family=INTELLIJ",
      "sha256": "tBLPoV7PWzCsS++iCUO8uGLwGG40+cemMPUlEZILVGo=",
      "channel": "stable",
      "dependencies": [
        "Tomcat",
        "com.intellij.javaee",
        "org.jetbrains.idea.maven"
      ],
      "optional_dependencies": [],
      "file_name": "hippo-shared-libs.zip"
    }
  },
  "latest": {
    "stable": "1.1.0"
  }
}