{
  "xml_id": "riderblockjumper-rider",
  "numeric_id": 14366,
  "versions": {
    "1.0.1": {
      "download_url": "https://downloads.marketplace.jetbrains.com/files/14366/86890/riderblockjumper-1.0.1.zip?updateId=86890&pluginId=14366&family=INTELLIJ",
      "sha256": "IJoRFxghr9OPae9pzYvVpJFbkKEj8UlwNE5+9nBuuFU=",
      "channel": "stable",
      "dependencies": [
        "com.intellij.modules.rider"
      ],
      "optional_dependencies": [],
      "file_name": "riderblockjumper-1.0.1.zip"
    }
  },
  "latest": {
    "stable": "1.0.1"
  }
}