{
  "xml_id": "za.co.sfy.angular.imports-sorter",
  "numeric_id": 10839,
  "versions": {
    "1.0": {
      "download_url": "https://downloads.marketplace.jetbrains.com/files/10839/46987/angular-import-sorter.jar?updateId=46987&pluginId=10839&family=INTELLIJ",
      "sha256": "5QdYWA7Erm6TYLOoAlC8VwOn1tMNfW9K0w9i+9EA4+E=",
      "channel": "stable",
      "dependencies": [],
      "optional_dependencies": [],
      "file_name": "angular-import-sorter.jar"
    }
  },
  "latest": {
    "stable": "1.0"
  }
}