{
  "xml_id": "com.coursehero.hodor",
  "numeric_id": 9539,
  "versions": {
    "1.0.0": {
      "download_url": "https://downloads.marketplace.jetbrains.com/files/9539/33221/HodorPlugin.zip?updateId=33221&pluginId=9539&family=INTELLIJ",
      "sha256": "KXK+O2B5Qugf90Ytmq+tdfXVsCpvOO3DPPlfCbMgWAU=",
      "channel": "stable",
      "dependencies": [
        "com.intellij.modules.lang",
        "com.intellij.modules.platform"
      ],
      "optional_dependencies": [],
      "file_name": "HodorPlugin.zip"
    }
  },
  "latest": {
    "stable": "1.0.0"
  }
}